README.rst
setup.py
li_traceroute/icmp_trace.py
li_traceroute/print_method.py
li_traceroute/socket_maker.py
li_traceroute/traceroute.py
li_traceroute/try_data.py
li_traceroute/udp_trace.py
li_traceroute.egg-info/PKG-INFO
li_traceroute.egg-info/SOURCES.txt
li_traceroute.egg-info/dependency_links.txt
li_traceroute.egg-info/entry_points.txt
li_traceroute.egg-info/not-zip-safe
li_traceroute.egg-info/requires.txt
li_traceroute.egg-info/top_level.txt