Metadata-Version: 1.0
Name: li-traceroute
Version: 1.6
Summary: python simple traceroute ICMP/UDP+ICMP for linux
Home-page: https://github.com/ShapeShifter420/li-traceroute
Author: UNKNOWN
Author-email: UNKNOWN
License: UNKNOWN
Platform: UNKNOWN
